torizon_templates_utils/__init__.py
torizon_templates_utils/animations.py
torizon_templates_utils/args.py
torizon_templates_utils/colors.py
torizon_templates_utils/debug.py
torizon_templates_utils/errors.py
torizon_templates_utils/network.py
torizon_templates_utils/tasks.py
torizon_templates_utils-1.1.4.dist-info/METADATA
torizon_templates_utils-1.1.4.dist-info/WHEEL
torizon_templates_utils-1.1.4.dist-info/top_level.txt
torizon_templates_utils-1.1.4.dist-info/RECORD
